{
    "blog": {
        "description": "Writing and Stuff from Isaac Z. Schlueter",
        "name": "izs",
        "title": "blog.izs.me",
        "updated": 1544578035,
        "url": "http://blog.izs.me/",
        "uuid": "t:qZa3tMNNGjX7PQ45aXJ-jw"
    },
    "blog_name": "izs",
    "can_like": false,
    "can_reblog": false,
    "can_reply": false,
    "can_send_in_message": true,
    "caption": "<p><a class=\"tumblr_blog\" href=\"http://raygorartshit.tumblr.com/post/95491797525/bisexual-frustration-everyone-is-hot-and-im\">raygorartshit</a>:</p>\n<blockquote>\n<p>Bisexual Frustration: Everyone is Hot and I\u2019m Really Bad at Handling It - my autobiography</p>\n</blockquote>",
    "date": "2014-09-14 19:58:04 GMT",
    "display_avatar": true,
    "format": "html",
    "id": 97500236773,
    "image_permalink": "http://blog.izs.me/image/97500236773",
    "is_blocks_post_format": false,
    "note_count": 97317,
    "photos": [
        {
            "alt_sizes": [
                {
                    "height": 1920,
                    "url": "https://66.media.tumblr.com/45d7fde9b8a77659d319d60e246679cc/tumblr_naqak0LQCU1sh41a5o1_1280.png",
                    "width": 815
                },
                {
                    "height": 960,
                    "url": "https://66.media.tumblr.com/45d7fde9b8a77659d319d60e246679cc/tumblr_naqak0LQCU1sh41a5o1_640.png",
                    "width": 408
                },
                {
                    "height": 810,
                    "url": "https://66.media.tumblr.com/45d7fde9b8a77659d319d60e246679cc/tumblr_naqak0LQCU1sh41a5o1_540.png",
                    "width": 344
                },
                {
                    "height": 750,
                    "url": "https://66.media.tumblr.com/45d7fde9b8a77659d319d60e246679cc/tumblr_naqak0LQCU1sh41a5o1_500.png",
                    "width": 318
                },
                {
                    "height": 600,
                    "url": "https://66.media.tumblr.com/45d7fde9b8a77659d319d60e246679cc/tumblr_naqak0LQCU1sh41a5o1_400.png",
                    "width": 255
                },
                {
                    "height": 400,
                    "url": "https://66.media.tumblr.com/45d7fde9b8a77659d319d60e246679cc/tumblr_naqak0LQCU1sh41a5o1_250.png",
                    "width": 170
                },
                {
                    "height": 200,
                    "url": "https://66.media.tumblr.com/45d7fde9b8a77659d319d60e246679cc/tumblr_naqak0LQCU1sh41a5o1_100.png",
                    "width": 85
                },
                {
                    "height": 75,
                    "url": "https://66.media.tumblr.com/45d7fde9b8a77659d319d60e246679cc/tumblr_naqak0LQCU1sh41a5o1_75sq.png",
                    "width": 75
                }
            ],
            "caption": "",
            "original_size": {
                "height": 1920,
                "url": "https://66.media.tumblr.com/45d7fde9b8a77659d319d60e246679cc/tumblr_naqak0LQCU1sh41a5o1_1280.png",
                "width": 815
            }
        }
    ],
    "post_url": "http://blog.izs.me/post/97500236773/raygorartshit-bisexual-frustration-everyone-is",
    "reblog": {
        "comment": "",
        "tree_html": "<p><a class=\"tumblr_blog\" href=\"http://raygorartshit.tumblr.com/post/95491797525/bisexual-frustration-everyone-is-hot-and-im\">raygorartshit</a>:</p><blockquote>\n<p>Bisexual Frustration: Everyone is Hot and I\u2019m Really Bad at Handling It - my autobiography</p>\n</blockquote>"
    },
    "reblog_key": "YQb8Vcjq",
    "reblogged_from_can_message": true,
    "reblogged_from_id": "97320647430",
    "reblogged_from_name": "sliversilence",
    "reblogged_from_title": "reblogs ok",
    "reblogged_from_url": "http://sliversilence.tumblr.com/post/97320647430/raygorartshit-bisexual-frustration-everyone-is",
    "reblogged_from_uuid": "t:3IRIUzLxZN3ZLpsFsDLgpg",
    "reblogged_root_can_message": true,
    "reblogged_root_id": "95491797525",
    "reblogged_root_name": "raygorartshit",
    "reblogged_root_title": "Raygor's Super Professional Art Blog",
    "reblogged_root_url": "http://raygorartshit.tumblr.com/post/95491797525/bisexual-frustration-everyone-is-hot-and-im",
    "reblogged_root_uuid": "t:YuMW9VgKeSrGKCjLmaYDiw",
    "recommended_color": null,
    "recommended_source": null,
    "short_url": "https://tmblr.co/Z7nwWy1QpTulb",
    "slug": "raygorartshit-bisexual-frustration-everyone-is",
    "source_title": "raygorartshit",
    "source_url": "http://raygorartshit.tumblr.com/post/95491797525/bisexual-frustration-everyone-is-hot-and-im",
    "state": "published",
    "summary": "Bisexual Frustration: Everyone is Hot and I\u2019m Really Bad at Handling It - my autobiography",
    "tags": [],
    "timestamp": 1410724684,
    "trail": [
        {
            "blog": {
                "active": true,
                "can_be_followed": true,
                "name": "raygorartshit",
                "share_following": false,
                "share_likes": false,
                "theme": {
                    "avatar_shape": "square",
                    "background_color": "#FAFAFA",
                    "body_font": "Helvetica Neue",
                    "header_bounds": "67,1143,683,48",
                    "header_focus_height": 616,
                    "header_focus_width": 1095,
                    "header_full_height": 1435,
                    "header_full_width": 1280,
                    "header_image": "https://static.tumblr.com/254842f0b7e929c8e2bcc2f8d5ac9a0a/ohxqiwc/ZjCobesiu/tumblr_static_.png",
                    "header_image_focused": "https://static.tumblr.com/254842f0b7e929c8e2bcc2f8d5ac9a0a/ohxqiwc/HpFobesiz/tumblr_static_tumblr_static__focused_v3.png",
                    "header_image_scaled": "https://static.tumblr.com/254842f0b7e929c8e2bcc2f8d5ac9a0a/ohxqiwc/ZjCobesiu/tumblr_static__2048_v2.png",
                    "header_stretch": true,
                    "link_color": "#529ECC",
                    "show_avatar": true,
                    "show_description": true,
                    "show_header_image": true,
                    "show_title": true,
                    "title_color": "#444444",
                    "title_font": "Gibson",
                    "title_font_weight": "bold"
                }
            },
            "content": "<p>Bisexual Frustration: Everyone is Hot and I&rsquo;m Really Bad at Handling It - my autobiography</p>",
            "content_raw": "<p>Bisexual Frustration: Everyone is Hot and I\u2019m Really Bad at Handling It - my autobiography</p>",
            "is_root_item": true,
            "post": {
                "id": "95491797525"
            }
        }
    ],
    "type": "photo"
}