{
    "blog": {
        "description": "Writing and Stuff from Isaac Z. Schlueter",
        "name": "izs",
        "title": "blog.izs.me",
        "updated": 1544051896,
        "url": "http://blog.izs.me/",
        "uuid": "t:qZa3tMNNGjX7PQ45aXJ-jw"
    },
    "blog_name": "izs",
    "body": "<p><a href=\"http://nodejsreactions.tumblr.com/post/56791389899/node-modules\" class=\"tumblr_blog\">nodejsreactions</a>:</p>\n\n<blockquote><p><img alt=\"image\" src=\"http://i.imgur.com/Ho7X0W0.gif\"/></p>\n<p>Submitted by <a href=\"https://twitter.com/shamakry\">@shamakry</a></p></blockquote>",
    "can_like": false,
    "can_reblog": false,
    "can_reply": false,
    "can_send_in_message": true,
    "date": "2013-07-29 23:49:09 GMT",
    "display_avatar": true,
    "format": "markdown",
    "id": 56825769839,
    "is_blocks_post_format": false,
    "note_count": 3,
    "post_url": "http://blog.izs.me/post/56825769839/nodemodules",
    "reblog": {
        "comment": "",
        "tree_html": "<p><a href=\"http://nodejsreactions.tumblr.com/post/56791389899/node-modules\" class=\"tumblr_blog\">nodejsreactions</a>:</p><blockquote>\n<p><img alt=\"image\" src=\"http://i.imgur.com/Ho7X0W0.gif\"></p>\n<p>Submitted by <a href=\"https://twitter.com/shamakry\">@shamakry</a></p>\n</blockquote>"
    },
    "reblog_key": "00CEx9b7",
    "reblogged_from_can_message": true,
    "reblogged_from_id": "56791389899",
    "reblogged_from_name": "nodejsreactions",
    "reblogged_from_title": "Node.js Reactions",
    "reblogged_from_url": "https://nodejsreactions.tumblr.com/post/56791389899/nodemodules",
    "reblogged_from_uuid": "t:BBN45R0sRTSVUu7T5ZNnVw",
    "reblogged_root_can_message": true,
    "reblogged_root_id": "56791389899",
    "reblogged_root_name": "nodejsreactions",
    "reblogged_root_title": "Node.js Reactions",
    "reblogged_root_url": "https://nodejsreactions.tumblr.com/post/56791389899/nodemodules",
    "reblogged_root_uuid": "t:BBN45R0sRTSVUu7T5ZNnVw",
    "recommended_color": null,
    "recommended_source": null,
    "short_url": "https://tmblr.co/Z7nwWyqx56zl",
    "slug": "nodemodules",
    "state": "published",
    "summary": "node_modules",
    "tags": [],
    "timestamp": 1375141749,
    "title": "node_modules",
    "trail": [
        {
            "blog": {
                "active": true,
                "can_be_followed": true,
                "name": "nodejsreactions",
                "share_following": false,
                "share_likes": true,
                "theme": {
                    "avatar_shape": "square",
                    "background_color": "#FAFAFA",
                    "body_font": "Helvetica Neue",
                    "header_bounds": "",
                    "header_image": "https://assets.tumblr.com/images/default_header/optica_pattern_07.png?_v=c52eb3e7fd4be5c98b8970b4c330d172",
                    "header_image_focused": "https://assets.tumblr.com/images/default_header/optica_pattern_07_focused_v3.png?_v=c52eb3e7fd4be5c98b8970b4c330d172",
                    "header_image_scaled": "https://assets.tumblr.com/images/default_header/optica_pattern_07_focused_v3.png?_v=c52eb3e7fd4be5c98b8970b4c330d172",
                    "header_stretch": true,
                    "link_color": "#529ECC",
                    "show_avatar": true,
                    "show_description": true,
                    "show_header_image": true,
                    "show_title": true,
                    "title_color": "#444444",
                    "title_font": "Gibson",
                    "title_font_weight": "bold"
                }
            },
            "content": "<p><div class=\"external-image-wrapper\" data-loading-text=\"Loading...\" data-src=\"http://i.imgur.com/Ho7X0W0.gif\">External image</div></p>\n<p>Submitted by <a href=\"https://twitter.com/shamakry\">@shamakry</a></p>",
            "content_raw": "<p><img alt=\"image\" src=\"http://i.imgur.com/Ho7X0W0.gif\"></p>\n<p>Submitted by <a href=\"https://twitter.com/shamakry\">@shamakry</a></p>",
            "is_root_item": true,
            "post": {
                "id": "56791389899"
            }
        }
    ],
    "type": "text"
}